LICENSE.txt
MANIFEST.in
README.rst
setup.cfg
setup.py
docs/.DS_Store
docs/Makefile
docs/README.md
docs/conf.py
docs/gendoc.sh
docs/index.rst
docs/project_description.md
docs/requirements.txt
docs/_static/.DS_Store
docs/_static/css/inferpy_theme.css
docs/_static/css/menu.min.css
docs/_static/css/segment.min.css
docs/_static/css/tab.min.css
docs/_static/css/tabs.css
docs/_static/img/.DS_Store
docs/_static/img/MoG.pdf
docs/_static/img/MoG.png
docs/_static/img/arch.png
docs/_static/img/linear_regression.pdf
docs/_static/img/linear_regression.png
docs/_static/img/logistic_regression.pdf
docs/_static/img/logistic_regression.png
docs/_static/img/logo-doc.png
docs/_static/img/logo-neg.png
docs/_static/img/logo.png
docs/_static/img/mixture_density_networks.rst
docs/_static/img/mnist_gen.png
docs/_static/img/mnist_train.png
docs/_static/img/multinomial_logistic_regression.pdf
docs/_static/img/multinomial_logistic_regression.png
docs/_static/img/nlpca.pdf
docs/_static/img/nlpca.png
docs/_static/img/pca.pdf
docs/_static/img/pca.png
docs/_static/img/pca_ard.pdf
docs/_static/img/pca_ard.png
docs/_static/img/postz_cloud.png
docs/_static/img/notebooks/.DS_Store
docs/_static/img/notebooks/output_10_0.png
docs/_static/img/notebooks/output_16_0.png
docs/_static/img/notebooks/output_17_0.png
docs/_static/img/notebooks/output_18_0.png
docs/_static/img/notebooks/output_3_0.png
docs/_static/img/notebooks/output_4_1.png
docs/_static/img/notebooks/output_7_0.png
docs/_static/img/notebooks/output_9_2.png
docs/_static/imgs/LinearFactor.png
docs/_static/imgs/LinearFactor_scaled.png
docs/_static/imgs/MatrixFactorization.png
docs/_static/imgs/MixedMembership.png
docs/_static/imgs/MoG.png
docs/modules/inferpy.contextmanager.rst
docs/modules/inferpy.data.rst
docs/modules/inferpy.inference.rst
docs/modules/inferpy.inference.variational.loss_functions.rst
docs/modules/inferpy.inference.variational.rst
docs/modules/inferpy.layers.rst
docs/modules/inferpy.models.rst
docs/modules/inferpy.queries.rst
inferpy.egg-info/PKG-INFO
inferpy.egg-info/SOURCES.txt
inferpy.egg-info/dependency_links.txt
inferpy.egg-info/requires.txt
inferpy.egg-info/top_level.txt
