Metadata-Version: 2.1
Name: inferpy
Version: 1.3.1
Summary: Deep Probabilistic modeling with Tensorflow made easy
Home-page: http://inferpy.readthedocs.io
Author: Andrés R. Masegosa, Rafael Cabañas, Javier Cózar
Author-email: andresma@ual.es, rcabanas@ual.es, jcozar87@ual.es
License: Apache License 2.0
Download-URL: https://github.com/PGMLabSpain/InferPy/archive/1.3.1.tar.gz
Keywords: machine learning statistics probabilistic programming tensorflow edward2
Platform: UNKNOWN
Classifier: Intended Audience :: Developers
Classifier: Intended Audience :: Education
Classifier: Intended Audience :: Science/Research
Classifier: License :: OSI Approved :: Apache Software License
Classifier: Operating System :: POSIX :: Linux
Classifier: Operating System :: MacOS :: MacOS X
Classifier: Operating System :: Microsoft :: Windows
Classifier: Programming Language :: Python :: 3.4
Requires-Python: >=3.5
Provides-Extra: gpu
Provides-Extra: all
Provides-Extra: datasets
Provides-Extra: all-gpu
Provides-Extra: visualization
